{
    "name": "ALLEGRAIN Christophe-Gabriel",
    "life": "(b. 1710 Paris d. 1795 Paris)",
    "school": "French",
    "timeframe": "1751-1800",
    "art": [
        {
            "title": "Venus at Bath",
            "date": "c. 1767",
            "technique": "Marble height 174 cm",
            "location": "Musée du Louvre Paris",
            "url": "https://www.wga.hu/html/a/allegrai/christop/venus_ba.html",
            "form": "sculpture",
            "painting_type": "mythological",
            "index": 320
        },
        {}
    ]
}