{
    "name": "ANDREANI Andrea",
    "life": "(b. ca. 1558 Mantova d. ca. 1629 Mantova)",
    "school": "Italian",
    "timeframe": "1551-1600",
    "art": [
        {
            "title": "The Triumph of Caesar (frontispiece)",
            "date": "1599",
            "technique": "Chiaroscuro woodcut 374 x 370 mm",
            "location": "British Museum London",
            "url": "https://www.wga.hu/html/a/andreani/triumph.html",
            "form": "graphics",
            "painting_type": "historical",
            "index": 698
        },
        {
            "title": "The Triumph of Caesar (Section 1)",
            "date": "1599",
            "technique": "Chiaroscuro woodcut 368 x 368 mm",
            "location": "British Museum London",
            "url": "https://www.wga.hu/html/a/andreani/triumph1.html",
            "form": "graphics",
            "painting_type": "historical",
            "index": 699
        },
        {
            "title": "The Triumph of Caesar (Section 3)",
            "date": "1599",
            "technique": "Chiaroscuro woodcut 368 x 375 mm",
            "location": "British Museum London",
            "url": "https://www.wga.hu/html/a/andreani/triumph3.html",
            "form": "graphics",
            "painting_type": "historical",
            "index": 700
        },
        {
            "title": "The Triumph of Caesar (Section 4)",
            "date": "1599",
            "technique": "Chiaroscuro woodcut 370 x 370 mm",
            "location": "British Museum London",
            "url": "https://www.wga.hu/html/a/andreani/triumph4.html",
            "form": "graphics",
            "painting_type": "historical",
            "index": 701
        },
        {
            "title": "The Triumph of Caesar (Section 5)",
            "date": "1599",
            "technique": "Chiaroscuro woodcut 365 x 375 mm",
            "location": "British Museum London",
            "url": "https://www.wga.hu/html/a/andreani/triumph5.html",
            "form": "graphics",
            "painting_type": "historical",
            "index": 702
        },
        {
            "title": "The Triumph of Caesar (Section 6)",
            "date": "1599",
            "technique": "Chiaroscuro woodcut 378 x 365 mm",
            "location": "British Museum London",
            "url": "https://www.wga.hu/html/a/andreani/triumph6.html",
            "form": "graphics",
            "painting_type": "historical",
            "index": 703
        },
        {
            "title": "The Triumph of Caesar (Section 7)",
            "date": "1599",
            "technique": "Chiaroscuro woodcut 365 x 368 mm",
            "location": "British Museum London",
            "url": "https://www.wga.hu/html/a/andreani/triumph7.html",
            "form": "graphics",
            "painting_type": "historical",
            "index": 704
        },
        {
            "title": "The Triumph of Caesar (Section 8)",
            "date": "1599",
            "technique": "Chiaroscuro woodcut 365 x 368 mm",
            "location": "British Museum London",
            "url": "https://www.wga.hu/html/a/andreani/triumph8.html",
            "form": "graphics",
            "painting_type": "historical",
            "index": 705
        },
        {
            "title": "The Triumph of Caesar (Section 9)",
            "date": "1599",
            "technique": "Chiaroscuro woodcut 370 x 379 mm",
            "location": "British Museum London",
            "url": "https://www.wga.hu/html/a/andreani/triumph9.html",
            "form": "graphics",
            "painting_type": "historical",
            "index": 706
        }
    ]
}