{
    "art": [
        {
            "index": 3663,
            "location": "Private collection",
            "img": "imgs/art/3663.jpg",
            "form": "painting",
            "url": "https://www.wga.hu/html/b/beert/younger/stillife.html",
            "title": "Still-Life",
            "author": "BEERT Osias the Younger",
            "technique": "Oil on panel 54 x 85 cm",
            "painting_type": "still-life",
            "date": "-"
        }
    ],
    "timeframe": "1651-1700",
    "life": "(b. 1622 Antwerpen d. ca. 1678 Antwerpen)",
    "name": "BEERT Osias the Younger",
    "school": "Flemish"
}