{
    "name": "BREGHTEL Hans Conraedt",
    "life": "(b. ca. 1608 N\u00fcrnberg d. 1675 Den Haag)",
    "school": "German",
    "timeframe": "1601-1650",
    "art": [
        {
            "title": "Clock",
            "date": "1665-70",
            "technique": "Silver and silver-gilt pierced embossed filigree height 92 cm",
            "location": "Victoria and Albert Museum London",
            "url": "https://www.wga.hu/html/b/breghtel/clock.html",
            "form": "metalwork",
            "painting_type": "other",
            "index": 6057
        },
        {
            "title": "Sconce",
            "date": "1647",
            "technique": "Silver parcel-gilt height 93 cm",
            "location": "Kremlin Museum Moscow",
            "url": "https://www.wga.hu/html/b/breghtel/sconce.html",
            "form": "metalwork",
            "painting_type": "other",
            "index": 6058
        }
    ]
}