{
    "art": [
        {
            "index": 8159,
            "location": "Museo de Bellas Artes Bilbao",
            "img": "imgs/art/8159.jpg",
            "form": "painting",
            "url": "https://www.wga.hu/html/c/castell/martyrdo.html",
            "title": "The Martyrdom of St Catherine of Alexandria",
            "author": "CASTELL\u00d3 Vicente",
            "technique": "Oil on canvas 157 x 2075 cm",
            "painting_type": "religious",
            "date": "c. 1617"
        }
    ],
    "timeframe": "1601-1650",
    "life": "(b. ca. 1588 Valencia d. ca. 1636 Valencia)",
    "name": "CASTELL\u00d3 Vicente",
    "school": "Spanish"
}