{
    "name": "CODAZZI Viviano",
    "life": "(b. 1604 Bergamo d. 1670 Roma)",
    "school": "Italian",
    "timeframe": "1601-1650",
    "art": [
        {
            "title": "Architectural View",
            "date": "1627",
            "technique": "Oil on canvas",
            "location": "Galleria degli Uffizi Florence",
            "url": "https://www.wga.hu/html/c/codazzi/archview.html",
            "form": "painting",
            "painting_type": "landscape",
            "index": 9188
        },
        {
            "title": "The Nativity in an Ancient Ruin",
            "date": "c. 1660",
            "technique": "Oil on copper 27 x 19 cm",
            "location": "Private collection",
            "url": "https://www.wga.hu/html/c/codazzi/nativit.html",
            "form": "painting",
            "painting_type": "religious",
            "index": 9189
        },
        {
            "title": "The Nativity in an Ancient Ruin (detail)",
            "date": "c. 1660",
            "technique": "Oil on copper",
            "location": "Private collection",
            "url": "https://www.wga.hu/html/c/codazzi/nativit1.html",
            "form": "painting",
            "painting_type": "religious",
            "index": 9190
        },
        {
            "title": "St Peter's Rome",
            "date": "c. 1630",
            "technique": "Oil on canvas 168 x 220 cm",
            "location": "Museo del Prado Madrid",
            "url": "https://www.wga.hu/html/c/codazzi/rome.html",
            "form": "painting",
            "painting_type": "landscape",
            "index": 9191
        },
        {
            "title": "Rome the Campo Vaccino Looking toward the Capitoline",
            "date": "c. 1630",
            "technique": "Oil on canvas 72 x 955 cm",
            "location": "Galleria dell'Accademia di San Luca Rome",
            "url": "https://www.wga.hu/html/c/codazzi/vaccino.html",
            "form": "painting",
            "painting_type": "landscape",
            "index": 9192
        }
    ]
}