{
    "name": "CRÉPIN Louis Philippe",
    "life": "(b. 1772 Paris d. 1851 Paris)",
    "school": "",
    "timeframe": "",
    "art": [
        {
            "title": "The Fight between the \"\"Lys\"\" and the \"\"Gloire\"\" against the \"\"Cumberland\"\"\"1827\"Oil on canvas 147 x 114 cm",
            "date": "Private collection",
            "technique": "https://www.wga.hu/html/c/crepin/battlesc.html",
            "location": "painting",
            "url": "historical",
            "form": "French",
            "painting_type": "1801-1850",
            "index": 10436
        },
        {
            "title": "A Boarding Scene",
            "date": "-",
            "technique": "Oil on canvas 147 x 114 cm",
            "location": "Private collection",
            "url": "https://www.wga.hu/html/c/crepin/boarding.html",
            "form": "painting",
            "painting_type": "historical",
            "index": 10437
        },
        {}
    ]
}