{
    "art": [
        {
            "index": 13792,
            "location": "Benedictine Abbey Church Zwiefalten",
            "img": "imgs/art/13792.jpg",
            "form": "architecture",
            "url": "https://www.wga.hu/html/f/feuchtma/johann/zwiefal.html",
            "title": "Interior view",
            "author": "FEUCHTMAYER Johann Michael the Younger",
            "technique": "Photo",
            "painting_type": "interior",
            "date": "1738-65"
        }
    ],
    "timeframe": "1701-1750",
    "life": "(b. 1709 Wessobrunn d. 1772 Augsburg)",
    "name": "FEUCHTMAYER Johann Michael the Younger",
    "school": "German"
}