{
    "name": "LOCHNER Stefan",
    "life": "(b. ca. 1400 Meersburg am Bodensee d. 1451 K\u00f6ln)",
    "school": "German",
    "timeframe": "1401-1450",
    "art": [
        {
            "title": "Altarpiece of the Patron Saints of Cologne",
            "date": "1440s",
            "technique": "Mixed technique on wood 260 x 185 cm (central) 261 x 142 cm (wings each)",
            "location": "Cathedral Cologne",
            "url": "https://www.wga.hu/html/l/lochner/adorat.html",
            "form": "painting",
            "painting_type": "religious",
            "index": 22788
        },
        {
            "title": "Adoration of the Magi",
            "date": "c. 1440",
            "technique": "Mixed technique on wood 260 x 185 cm",
            "location": "Cathedral Cologne",
            "url": "https://www.wga.hu/html/l/lochner/adorati.html",
            "form": "painting",
            "painting_type": "religious",
            "index": 22789
        },
        {
            "title": "Adoration of the Child Jesus",
            "date": "1445",
            "technique": "Wood 36 x 23 cm",
            "location": "Alte Pinakothek Munich",
            "url": "https://www.wga.hu/html/l/lochner/adoratio.html",
            "form": "painting",
            "painting_type": "religious",
            "index": 22790
        },
        {
            "title": "Martyrdom of the Apostles Altarpiece (interior left wing)",
            "date": "1435-40",
            "technique": "Oil on panel 120 x 80 cm",
            "location": "St\u00e4delsches Kunstinstitut Frankfurt",
            "url": "https://www.wga.hu/html/l/lochner/apostles.html",
            "form": "painting",
            "painting_type": "religious",
            "index": 22791
        },
        {
            "title": "Sts Anthony the Hermit Cornelius and Mary Magdalen with a Donor",
            "date": "c. 1445",
            "technique": "Walnut panel 120 x 80 cm",
            "location": "Alte Pinakothek Munich",
            "url": "https://www.wga.hu/html/l/lochner/catherin.html",
            "form": "painting",
            "painting_type": "religious",
            "index": 22792
        },
        {
            "title": "The Last Judgment",
            "date": "c. 1435",
            "technique": "Oak 1245 x 172 cm",
            "location": "Wallraf-Richartz-Museum Cologne",
            "url": "https://www.wga.hu/html/l/lochner/lastjudg.html",
            "form": "painting",
            "painting_type": "religious",
            "index": 22793
        },
        {
            "title": "Madonna of the Rose Garden",
            "date": "c. 1440",
            "technique": "Oil on panel 51 x 40 cm",
            "location": "Wallraf-Richartz-Museum Cologne",
            "url": "https://www.wga.hu/html/l/lochner/madonna.html",
            "form": "painting",
            "painting_type": "religious",
            "index": 22794
        },
        {
            "title": "Presentation of Christ in the Temple",
            "date": "1447",
            "technique": "Panel",
            "location": "Hessisches Landesmuseum Darmstadt",
            "url": "https://www.wga.hu/html/l/lochner/present.html",
            "form": "painting",
            "painting_type": "religious",
            "index": 22795
        },
        {
            "title": "Presentation of Christ in the Temple (detail)",
            "date": "1447",
            "technique": "Panel",
            "location": "Hessisches Landesmuseum Darmstadt",
            "url": "https://www.wga.hu/html/l/lochner/present1.html",
            "form": "painting",
            "painting_type": "religious",
            "index": 22796
        },
        {
            "title": "Presentation of Christ in the Temple (detail)",
            "date": "1447",
            "technique": "Panel",
            "location": "Hessisches Landesmuseum Darmstadt",
            "url": "https://www.wga.hu/html/l/lochner/present2.html",
            "form": "painting",
            "painting_type": "religious",
            "index": 22797
        },
        {
            "title": "Sts Mark Barbara and Luke",
            "date": "1445-50",
            "technique": "Panel 1005 x 58 cm",
            "location": "Wallraf-Richartz-Museum Cologne",
            "url": "https://www.wga.hu/html/l/lochner/saints.html",
            "form": "painting",
            "painting_type": "religious",
            "index": 22798
        },
        {
            "title": "Triptych with the Virgin and Child in an Enclosed garden",
            "date": "1445-50",
            "technique": "Oil on oak panel 313 x 2275 cm (central) 306 x 103 cm (each wing)",
            "location": "Wallraf-Richartz-Museum Cologne",
            "url": "https://www.wga.hu/html/l/lochner/triptych.html",
            "form": "painting",
            "painting_type": "religious",
            "index": 22799
        },
        {
            "title": "Prayer Book",
            "date": "1451",
            "technique": "Manuscript (Ms. 70) 108 x 80 mm",
            "location": "Hessische Landesbibliothek Darmstadt",
            "url": "https://www.wga.hu/html/l/lochner/zprayer1.html",
            "form": "illumination",
            "painting_type": "religious",
            "index": 22800
        },
        {
            "title": "Prayer Book",
            "date": "1451",
            "technique": "Manuscript (Ms. 70) 108 x 80 mm",
            "location": "Hessische Landesbibliothek Darmstadt",
            "url": "https://www.wga.hu/html/l/lochner/zprayer2.html",
            "form": "illumination",
            "painting_type": "religious",
            "index": 22801
        },
        {
            "title": "Prayer Book",
            "date": "1451",
            "technique": "Manuscript (Ms. 70) 108 x 80 mm",
            "location": "Hessische Landesbibliothek Darmstadt",
            "url": "https://www.wga.hu/html/l/lochner/zprayer3.html",
            "form": "illumination",
            "painting_type": "religious",
            "index": 22802
        },
        {}
    ]
}