{
    "name": "MAAS Dirk",
    "life": "(b. 1659 Haarlem d. 1717 Haarlem)",
    "school": "Dutch",
    "timeframe": "1651-1700",
    "art": [
        {
            "title": "Cavalry Encounter",
            "date": "1680s",
            "technique": "Oil on canvas 86 x 108 cm",
            "location": "The Hermitage St. Petersburg",
            "url": "https://www.wga.hu/html/m/maas/cavalry.html",
            "form": "painting",
            "painting_type": "historical",
            "index": 23510
        }
    ]
}