{
    "name": "PACKX Hendrick Ambrosius",
    "life": "(b. ca. 1603 Amsterdam d. after 1658)",
    "school": "Dutch",
    "timeframe": "1601-1650",
    "art": [
        {
            "title": "The Princes of Orange and Their Families Riding Out from the Buitenhof",
            "date": "1623-25",
            "technique": "Oil on canvas 145 x 214 cm",
            "location": "Mauritshuis The Hague",
            "url": "https://www.wga.hu/html/p/packx/princes.html",
            "form": "painting",
            "painting_type": "portrait",
            "index": 30099
        },
        {}
    ]
}