{
    "name": "RAMSAY Allan",
    "life": "(b. 1713 Edinburgh d. 1784 Dover)",
    "school": "Scottish",
    "timeframe": "1751-1800",
    "art": [
        {
            "title": "Queen Charlotte with her Two Children",
            "date": "c. 1765",
            "technique": "Oil on canvas 249 x 162 cm",
            "location": "Royal Collection Windsor",
            "url": "https://www.wga.hu/html/r/ramsay/charlott.html",
            "form": "painting",
            "painting_type": "portrait",
            "index": 33237
        },
        {
            "title": "Portrait of David Hume",
            "date": "1766",
            "technique": "Oil on canvas",
            "location": "Scottish National Portrait Gallery Edinburgh",
            "url": "https://www.wga.hu/html/r/ramsay/d_hume.html",
            "form": "painting",
            "painting_type": "portrait",
            "index": 33238
        },
        {
            "title": "Portrait of George III",
            "date": "c. 1762",
            "technique": "Oil on canvas 803 x 643 cm",
            "location": "National Portrait Gallery London",
            "url": "https://www.wga.hu/html/r/ramsay/george3.html",
            "form": "painting",
            "painting_type": "portrait",
            "index": 33239
        },
        {
            "title": "Prince George Augustus of Mecklenburg-Strelitz",
            "date": "c. 1769",
            "technique": "Oil on canvas 127 x 1016 cm",
            "location": "Royal Collection Windsor",
            "url": "https://www.wga.hu/html/r/ramsay/mecklenb.html",
            "form": "painting",
            "painting_type": "portrait",
            "index": 33240
        },
        {
            "title": "Portrait of the Artist's Wife",
            "date": "1754-55",
            "technique": "Oil on canvas 76 x 64 cm",
            "location": "National Gallery of Scotland Edinburgh",
            "url": "https://www.wga.hu/html/r/ramsay/portwife.html",
            "form": "painting",
            "painting_type": "portrait",
            "index": 33241
        },
        {
            "title": "Portrait of Lady Hariot Vernon",
            "date": "1742",
            "technique": "Oil on canvas 116 x 112 cm",
            "location": "Private collection",
            "url": "https://www.wga.hu/html/r/ramsay/vernon.html",
            "form": "painting",
            "painting_type": "portrait",
            "index": 33242
        }
    ]
}