{
    "name": "ROSSELLI Cosimo",
    "life": "(b. 1439 Firenze d. 1507 Firenze)",
    "school": "Italian",
    "timeframe": "1451-1500",
    "art": [
        {
            "title": "Crossing of the Red Sea",
            "date": "1481-82",
            "technique": "Fresco 350 x 572 cm",
            "location": "Cappella Sistina Vatican",
            "url": "https://www.wga.hu/html/r/rosselli/cosimo/crossing.html",
            "form": "painting",
            "painting_type": "religious",
            "index": 35147
        },
        {
            "title": "The Last Supper",
            "date": "1481-82",
            "technique": "Fresco 349 x 570 cm",
            "location": "Cappella Sistina Vatican",
            "url": "https://www.wga.hu/html/r/rosselli/cosimo/lastsup.html",
            "form": "painting",
            "painting_type": "religious",
            "index": 35148
        },
        {
            "title": "The Last Supper (detail)",
            "date": "1481-82",
            "technique": "Fresco",
            "location": "Cappella Sistina Vatican",
            "url": "https://www.wga.hu/html/r/rosselli/cosimo/lastsup1.html",
            "form": "painting",
            "painting_type": "religious",
            "index": 35149
        },
        {
            "title": "The Last Supper (detail)",
            "date": "1481-82",
            "technique": "Fresco",
            "location": "Cappella Sistina Vatican",
            "url": "https://www.wga.hu/html/r/rosselli/cosimo/lastsup2.html",
            "form": "painting",
            "painting_type": "religious",
            "index": 35150
        },
        {
            "title": "The Last Supper (detail)",
            "date": "1481-82",
            "technique": "Fresco",
            "location": "Cappella Sistina Vatican",
            "url": "https://www.wga.hu/html/r/rosselli/cosimo/lastsup3.html",
            "form": "painting",
            "painting_type": "religious",
            "index": 35151
        },
        {
            "title": "The Last Supper (detail)",
            "date": "1481-82",
            "technique": "Fresco",
            "location": "Cappella Sistina Vatican",
            "url": "https://www.wga.hu/html/r/rosselli/cosimo/lastsup4.html",
            "form": "painting",
            "painting_type": "religious",
            "index": 35152
        },
        {
            "title": "The Last Supper (detail)",
            "date": "1481-82",
            "technique": "Fresco",
            "location": "Cappella Sistina Vatican",
            "url": "https://www.wga.hu/html/r/rosselli/cosimo/lastsup5.html",
            "form": "painting",
            "painting_type": "religious",
            "index": 35153
        },
        {
            "title": "Sermon on the Mount",
            "date": "1481-82",
            "technique": "Fresco 349 x 570 cm",
            "location": "Cappella Sistina Vatican",
            "url": "https://www.wga.hu/html/r/rosselli/cosimo/sermon.html",
            "form": "painting",
            "painting_type": "religious",
            "index": 35154
        },
        {
            "title": "Tables of the Law with the Golden Calf",
            "date": "1481-82",
            "technique": "Fresco 350 x 572 cm",
            "location": "Cappella Sistina Vatican",
            "url": "https://www.wga.hu/html/r/rosselli/cosimo/tables.html",
            "form": "painting",
            "painting_type": "religious",
            "index": 35155
        },
        {
            "title": "Scene from the Life of St Filippo Benizzi",
            "date": "c. 1475",
            "technique": "Fresco",
            "location": "Santissima Annunziata Florence",
            "url": "https://www.wga.hu/html/r/rosselli/cosimo/zbenizzi.html",
            "form": "painting",
            "painting_type": "religious",
            "index": 35156
        },
        {
            "title": "Crucifixion with the Madonna and Saints",
            "date": "1503",
            "technique": "Oil on panel 207 x 193 cm",
            "location": "Private collection",
            "url": "https://www.wga.hu/html/r/rosselli/cosimo/zcrucifi.html",
            "form": "painting",
            "painting_type": "religious",
            "index": 35157
        },
        {
            "title": "Descent from Cross",
            "date": "c. 1485",
            "technique": "Oil and tempera on panel 51 x 36 cm",
            "location": "Museum of Fine Arts Boston Boston",
            "url": "https://www.wga.hu/html/r/rosselli/cosimo/zdescent.html",
            "form": "painting",
            "painting_type": "religious",
            "index": 35158
        },
        {
            "title": "Madonna and Child with Angels",
            "date": "1480-82",
            "technique": "Tempera gold on panel 85 x 58 cm",
            "location": "Metropolitan Museum of Art New York",
            "url": "https://www.wga.hu/html/r/rosselli/cosimo/zmadonna.html",
            "form": "painting",
            "painting_type": "religious",
            "index": 35159
        },
        {
            "title": "Portrait of a Man",
            "date": "c. 1485",
            "technique": "Tempera on wood 52 x 34 cm",
            "location": "Metropolitan Museum of Art New York",
            "url": "https://www.wga.hu/html/r/rosselli/cosimo/zportrai.html",
            "form": "painting",
            "painting_type": "portrait",
            "index": 35160
        }
    ]
}